[
  {
    "video_id": "0001",
    "source": "MrZygy3",
    "url": "https://www.youtube.com/watch?v=jsxYPqyK4Bs",
    "fps": 6,
    "plates": [
      {
        "label": "AB8381FU",
        "frame_start": 750,
        "frame_end": 810,
        "frames": []
      },
      {
        "label": "AB8812VK",
        "frame_start": 960,
        "frame_end": 1020,
        "frames": []
      },
      {
        "label": "AB8360DT",
        "frame_start": 1350,
        "frame_end": 1376,
        "frames": []
      },
      {
        "label": "AB8667EU",
        "frame_start": 1920,
        "frame_end": 1967,
        "frames": []
      },
      {
        "label": "AB8437BY",
        "frame_start": 2640,
        "frame_end": 2730,
        "frames": []
      },
      {
        "label": "G1618JA",
        "frame_start": 2823,
        "frame_end": 2898,
        "frames": []
      },
      {
        "label": "AB9260HN",
        "frame_start": 3015,
        "frame_end": 3075,
        "frames": []
      },
      {
        "label": "AB9821ZN",
        "frame_start": 3480,
        "frame_end": 3540,
        "frames": []
      },
      {
        "label": "AB8715AY",
        "frame_start": 3810,
        "frame_end": 3870,
        "frames": []
      },
      {
        "label": "AD1486ZJ",
        "frame_start": 4020,
        "frame_end": 4080,
        "frames": []
      },
      {
        "label": "BE9294BA",
        "frame_start": 4135,
        "frame_end": 4175,
        "frames": []
      },
      {
        "label": "AD1322KJ",
        "frame_start": 6050,
        "frame_end": 6075,
        "frames": []
      },
      {
        "label": "AD1377HJ",
        "frame_start": 6485,
        "frame_end": 6530,
        "frames": []
      },
      {
        "label": "AD1623ZJ",
        "frame_start": 6760,
        "frame_end": 6785,
        "frames": []
      },
      {
        "label": "AD1640LB",
        "frame_start": 6850,
        "frame_end": 6890,
        "frames": []
      },
      {
        "label": "AD1322KJ",
        "frame_start": 7255,
        "frame_end": 7290,
        "frames": []
      },
      {
        "label": "AD1377HJ",
        "frame_start": 7370,
        "frame_end": 7430,
        "frames": []
      },
      {
        "label": "AD1306XJ",
        "frame_start": 7885,
        "frame_end": 7915,
        "frames": []
      },
      {
        "label": "AD1623ZJ",
        "frame_start": 8115,
        "frame_end": 8130,
        "frames": []
      },
      {
        "label": "AA1832EB",
        "frame_start": 8368,
        "frame_end": 8390,
        "frames": []
      },
      {
        "label": "AB8510EU",
        "frame_start": 8765,
        "frame_end": 8790,
        "frames": []
      },
      {
        "label": "AD1641PJ",
        "frame_start": 8790,
        "frame_end": 8815,
        "frames": []
      },
      {
        "label": "AB8557FU",
        "frame_start": 9680,
        "frame_end": 9715,
        "frames": []
      },
      {
        "label": "AB8489FU",
        "frame_start": 10130,
        "frame_end": 10165,
        "frames": []
      },
      {
        "label": "AB8689OE",
        "frame_start": 10445,
        "frame_end": 10470,
        "frames": []
      },
      {
        "label": "H1912GY",
        "frame_start": 10685,
        "frame_end": 10715,
        "frames": []
      },
      {
        "label": "B9856PDD",
        "frame_start": 11000,
        "frame_end": 11070,
        "frames": []
      },
      {
        "label": "AB9285FN",
        "frame_start": 11745,
        "frame_end": 11790,
        "frames": []
      },
      {
        "label": "AB8651OF",
        "frame_start": 12365,
        "frame_end": 12415,
        "frames": []
      },
      {
        "label": "AB9285FN",
        "frame_start": 12590,
        "frame_end": 12665,
        "frames": []
      },
      {
        "label": "AB8250ZY",
        "frame_start": 15825,
        "frame_end": 15905,
        "frames": []
      },
      {
        "label": "AB8841HN",
        "frame_start": 16555,
        "frame_end": 16650,
        "frames": []
      },
      {
        "label": "G1618JA",
        "frame_start": 17025,
        "frame_end": 17045,
        "frames": []
      },
      {
        "label": "AB9620HN",
        "frame_start": 17050,
        "frame_end": 17110,
        "frames": []
      },
      {
        "label": "AB8629OE",
        "frame_start": 20870,
        "frame_end": 20920,
        "frames": []
      },
      {
        "label": "AB8775OE",
        "frame_start": 21020,
        "frame_end": 21100,
        "frames": []
      },
      {
        "label": "AB8921ZN",
        "frame_start": 21120,
        "frame_end": 21145,
        "frames": []
      },
      {
        "label": "AB9402GD",
        "frame_start": 21865,
        "frame_end": 21900,
        "frames": []
      },
      {
        "label": "AB8167JH",
        "frame_start": 22490,
        "frame_end": 22530,
        "frames": []
      },
      {
        "label": "AB8421FU",
        "frame_start": 22760,
        "frame_end": 22810,
        "frames": []
      },
      {
        "label": "AB8520QF",
        "frame_start": 23895,
        "frame_end": 23940,
        "frames": []
      },
      {
        "label": "AB8905UK",
        "frame_start": 24842,
        "frame_end": 24880,
        "frames": []
      },
      {
        "label": "AD1640LB",
        "frame_start": 25158,
        "frame_end": 25198,
        "frames": []
      },
      {
        "label": "AB8266YK",
        "frame_start": 26710,
        "frame_end": 26770,
        "frames": []
      },
      {
        "label": "AB8161DT",
        "frame_start": 26525,
        "frame_end": 26570,
        "frames": []
      }
    ]
  }
]