<annotation>
    <folder>frames</folder>
    <filename>0001_755_AB8381FU.jpeg</filename>
    <size>
        <width>1920</width>
        <height>1080</height>
        <depth>3</depth>
    </size>
    <object>
        <name>plate-single_axle</name>
        <pose>Unspecified</pose>
        <truncated>0</truncated>
        <occluded>0</occluded>
        <difficult>0</difficult>
        <bndbox>
            <xmin>459.760925</xmin>
            <ymin>997.076843</ymin>
            <xmax>658.657288</xmax>
            <ymax>1068.011108</ymax>
        </bndbox>
    </object>
</annotation>