<annotation>
    <folder>frames</folder>
    <filename>0001_16560_AB8841HN.jpeg</filename>
    <size>
        <width>1920</width>
        <height>1080</height>
        <depth>3</depth>
    </size>
    <object>
        <name>plate</name>
        <pose>Unspecified</pose>
        <truncated>0</truncated>
        <occluded>0</occluded>
        <difficult>0</difficult>
        <bndbox>
            <xmin>733.618225</xmin>
            <ymin>812.248169</ymin>
            <xmax>1014.471863</xmax>
            <ymax>907.160217</ymax>
        </bndbox>
    </object>
</annotation>